realdata/__init__.py
realdata-0.1.1.dist-info/LICENSE
realdata-0.1.1.dist-info/METADATA
realdata-0.1.1.dist-info/WHEEL
realdata-0.1.1.dist-info/entry_points.txt
realdata-0.1.1.dist-info/top_level.txt
realdata-0.1.1.dist-info/RECORD
