Metadata-Version: 2.1
Name: realdata
Version: 0.1.1
Summary: Get real univariate time series data easily for testing
Home-page: https://github.com/microprediction/realdata
Author: microprediction
Author-email: pcotton@intechinvestments.com
License: MIT
Platform: UNKNOWN
Classifier: License :: OSI Approved :: MIT License
Classifier: Programming Language :: Python :: 3
Classifier: Programming Language :: Python :: 3.7
Requires-Dist: timemachines (>=0.15.0)
Requires-Dist: pandas
